Adafruit_MPR121/MPR121.py
Adafruit_MPR121/__init__.py
Adafruit_MPR121-1.1.2.dist-info/metadata.json
Adafruit_MPR121-1.1.2.dist-info/METADATA
Adafruit_MPR121-1.1.2.dist-info/RECORD
Adafruit_MPR121-1.1.2.dist-info/WHEEL
Adafruit_MPR121-1.1.2.dist-info/DESCRIPTION.rst
Adafruit_MPR121-1.1.2.dist-info/dependency_links.txt
Adafruit_MPR121-1.1.2.dist-info/top_level.txt
